keras_aug/__init__.py
keras_aug/_src/keras_aug_export.py
keras_aug/_src/version.py
keras_aug/_src/backend/__init__.py
keras_aug/_src/backend/bounding_box.py
keras_aug/_src/backend/bounding_box_test.py
keras_aug/_src/backend/dynamic_backend.py
keras_aug/_src/backend/image.py
keras_aug/_src/backend/image_test.py
keras_aug/_src/layers/__init__.py
keras_aug/_src/layers/base/__init__.py
keras_aug/_src/layers/base/vision_random_layer.py
keras_aug/_src/layers/base/vision_random_layer_test.py
keras_aug/_src/layers/composition/__init__.py
keras_aug/_src/layers/composition/random_apply.py
keras_aug/_src/layers/composition/random_apply_test.py
keras_aug/_src/layers/composition/random_choice.py
keras_aug/_src/layers/composition/random_choice_test.py
keras_aug/_src/layers/composition/random_order.py
keras_aug/_src/layers/composition/random_order_test.py
keras_aug/_src/layers/vision/__init__.py
keras_aug/_src/layers/vision/center_crop.py
keras_aug/_src/layers/vision/center_crop_test.py
keras_aug/_src/layers/vision/color_jitter.py
keras_aug/_src/layers/vision/color_jitter_test.py
keras_aug/_src/layers/vision/cut_mix.py
keras_aug/_src/layers/vision/cut_mix_test.py
keras_aug/_src/layers/vision/gaussian_blur.py
keras_aug/_src/layers/vision/gaussian_blur_test.py
keras_aug/_src/layers/vision/gaussian_noise.py
keras_aug/_src/layers/vision/gaussian_noise_test.py
keras_aug/_src/layers/vision/identity.py
keras_aug/_src/layers/vision/identity_test.py
keras_aug/_src/layers/vision/max_bounding_box.py
keras_aug/_src/layers/vision/max_bounding_box_test.py
keras_aug/_src/layers/vision/mix_up.py
keras_aug/_src/layers/vision/mix_up_test.py
keras_aug/_src/layers/vision/mosaic.py
keras_aug/_src/layers/vision/mosaic_test.py
keras_aug/_src/layers/vision/normalize.py
keras_aug/_src/layers/vision/normalize_test.py
keras_aug/_src/layers/vision/pad.py
keras_aug/_src/layers/vision/pad_test.py
keras_aug/_src/layers/vision/rand_augment.py
keras_aug/_src/layers/vision/rand_augment_test.py
keras_aug-1.1.1.dist-info/LICENSE
keras_aug-1.1.1.dist-info/METADATA
keras_aug-1.1.1.dist-info/WHEEL
keras_aug-1.1.1.dist-info/top_level.txt
keras_aug-1.1.1.dist-info/RECORD
