Metadata-Version: 2.1
Name: keras-aug
Version: 1.1.1
Summary: A library that includes Keras 3 preprocessing and augmentation layers
Author-email: Hong-Yu Chiu <james77777778@gmail.com>
Maintainer-email: Hong-Yu Chiu <james77777778@gmail.com>
License: Apache License 2.0
Project-URL: Homepage, https://github.com/james77777778/keras-aug
Project-URL: Documentation, https://github.com/james77777778/keras-aug
Project-URL: Repository, https://github.com/james77777778/keras-aug.git
Project-URL: Issues, https://github.com/james77777778/keras-aug/issues
Keywords: deep-learning,preprocessing,augmentation,keras,jax,tensorflow,torch
Classifier: Programming Language :: Python
Classifier: Programming Language :: Python :: 3
Classifier: Programming Language :: Python :: 3.9
Classifier: Programming Language :: Python :: 3.10
Classifier: Programming Language :: Python :: 3.11
Classifier: Programming Language :: Python :: 3.12
Classifier: Programming Language :: Python :: 3 :: Only
Classifier: Operating System :: Unix
Classifier: Operating System :: MacOS
Classifier: Intended Audience :: Science/Research
Classifier: Topic :: Scientific/Engineering
Classifier: Topic :: Software Development
Requires-Python: >=3.9
License-File: LICENSE
Requires-Dist: keras
Provides-Extra: tests
Requires-Dist: isort ; extra == 'tests'
Requires-Dist: ruff ; extra == 'tests'
Requires-Dist: black ; extra == 'tests'
Requires-Dist: pytest ; extra == 'tests'
Requires-Dist: pytest-cov ; extra == 'tests'
Requires-Dist: coverage ; extra == 'tests'
Requires-Dist: pre-commit ; extra == 'tests'
Requires-Dist: namex ; extra == 'tests'
